cython_xinput/__init__.py
cython_xinput/py.typed
cython_xinput/x.pyd
cython_xinput/x.pyi
cython_xinput/x.pyx
cython_xinput/xinput.pxd
cython_xinput-0.1.0.dist-info/METADATA
cython_xinput-0.1.0.dist-info/WHEEL
cython_xinput-0.1.0.dist-info/licenses/LICENSE
cython_xinput-0.1.0.dist-info/RECORD
