Metadata-Version: 2.1
Name: cython_xinput
Version: 0.1.0
Keywords: Windows,Xbox,Gamepad,xinput
Author-Email: Artur Drogunow <Artur.Drogunow@zf.com>
License: MIT
Classifier: Development Status :: 4 - Beta
Classifier: License :: OSI Approved :: MIT License
Classifier: Programming Language :: Python :: 3 :: Only
Classifier: Programming Language :: Cython
Classifier: Operating System :: Microsoft :: Windows
Project-URL: Issues, https://github.com/zariiii9003/cython_xinput/issues
Project-URL: Source, https://github.com/zariiii9003/cython_xinput
Project-URL: Homepage, https://github.com/zariiii9003/cython_xinput
Requires-Python: >=3.7
